bluesky_kafka/__init__.py
bluesky_kafka/_version.py
bluesky_kafka/consume.py
bluesky_kafka/mongo_normalized_consumer.py
bluesky_kafka/produce.py
bluesky_kafka/utils.py
bluesky_kafka/tests/__init__.py
bluesky_kafka/tests/conftest.py
bluesky_kafka/tests/test_basic_consumer.py
bluesky_kafka/tests/test_basic_producer.py
bluesky_kafka/tests/test_basics_in_single_process.py
bluesky_kafka/tests/test_bluesky_consumer.py
bluesky_kafka/tests/test_in_single_process.py
bluesky_kafka/tests/test_mongo_consumer.py
bluesky_kafka/tests/test_publisher.py
bluesky_kafka/tests/test_queue_thread.py
bluesky_kafka/tests/test_utils.py
bluesky_kafka/tools/__init__.py
bluesky_kafka/tools/queue_thread.py
bluesky_kafka-0.10.0.dist-info/AUTHORS.rst
bluesky_kafka-0.10.0.dist-info/LICENSE
bluesky_kafka-0.10.0.dist-info/METADATA
bluesky_kafka-0.10.0.dist-info/WHEEL
bluesky_kafka-0.10.0.dist-info/top_level.txt
bluesky_kafka-0.10.0.dist-info/RECORD
