Metadata-Version: 2.1
Name: bluesky-kafka
Version: 0.10.0
Summary: Kafka integration for bluesky.
Home-page: https://github.com/bluesky/bluesky-kafka
Author: Brookhaven National Lab
Author-email: jlynch@bnl.gov
License: BSD (3-clause)
Classifier: Development Status :: 2 - Pre-Alpha
Classifier: Natural Language :: English
Classifier: Programming Language :: Python :: 3
Requires-Python: >=3.6
License-File: LICENSE
License-File: AUTHORS.rst
